[{
  "dateTime" : "10/18/21 00:00:00",
  "value" : "56"
},{
  "dateTime" : "10/19/21 00:00:00",
  "value" : "38"
},{
  "dateTime" : "10/20/21 00:00:00",
  "value" : "0"
},{
  "dateTime" : "10/21/21 00:00:00",
  "value" : "16"
},{
  "dateTime" : "10/22/21 00:00:00",
  "value" : "10"
},{
  "dateTime" : "10/23/21 00:00:00",
  "value" : "61"
},{
  "dateTime" : "10/24/21 00:00:00",
  "value" : "20"
},{
  "dateTime" : "10/25/21 00:00:00",
  "value" : "4"
},{
  "dateTime" : "10/26/21 00:00:00",
  "value" : "0"
},{
  "dateTime" : "10/27/21 00:00:00",
  "value" : "19"
},{
  "dateTime" : "10/28/21 00:00:00",
  "value" : "0"
},{
  "dateTime" : "10/29/21 00:00:00",
  "value" : "41"
},{
  "dateTime" : "10/30/21 00:00:00",
  "value" : "27"
},{
  "dateTime" : "10/31/21 00:00:00",
  "value" : "34"
},{
  "dateTime" : "11/01/21 00:00:00",
  "value" : "19"
},{
  "dateTime" : "11/02/21 00:00:00",
  "value" : "0"
},{
  "dateTime" : "11/03/21 00:00:00",
  "value" : "0"
},{
  "dateTime" : "11/04/21 00:00:00",
  "value" : "0"
},{
  "dateTime" : "11/05/21 00:00:00",
  "value" : "5"
},{
  "dateTime" : "11/06/21 00:00:00",
  "value" : "127"
},{
  "dateTime" : "11/07/21 00:00:00",
  "value" : "45"
},{
  "dateTime" : "11/08/21 00:00:00",
  "value" : "29"
},{
  "dateTime" : "11/09/21 00:00:00",
  "value" : "0"
},{
  "dateTime" : "11/10/21 00:00:00",
  "value" : "2"
},{
  "dateTime" : "11/11/21 00:00:00",
  "value" : "28"
},{
  "dateTime" : "11/12/21 00:00:00",
  "value" : "51"
},{
  "dateTime" : "11/13/21 00:00:00",
  "value" : "46"
},{
  "dateTime" : "11/14/21 00:00:00",
  "value" : "36"
},{
  "dateTime" : "11/15/21 00:00:00",
  "value" : "22"
},{
  "dateTime" : "11/16/21 00:00:00",
  "value" : "10"
}]